Workbook

Sheet Dashboard
A1: ZEKER ZZP — Kwartaaloverzicht
A2: Vul dit template in via zeker-zzp.nl → Kwartaaltool → Excel exporteren
A4: SAMENVATTING
A5: 💰 Totale inkomsten (excl. BTW) | D5: =SUM(Inkomsten!E:E)-SUM(Inkomsten!E1:E4)
A6: 💸 Totale uitgaven (excl. BTW) | D6: =SUM(Uitgaven!E:E)-SUM(Uitgaven!E1:E4)
A7: 📊 Winst (excl. BTW) | D7: =D5-D6
A8: 🧾 BTW-saldo (te betalen / terug) | D8: =(SUM(Inkomsten!G:G)-SUM(Inkomsten!G1:G4))-(SUM(Uitgaven!G:G)-SUM(Uitgaven!G1:G4))
A9: 💵 Netto in je zak | D9: =D7-IF(D8>0,D8,0)
A12: BTW-DEADLINES 2025
A13: K1 (jan - mrt) | E13: 30 april 2025
A14: K2 (apr - jun) | E14: 31 juli 2025
A15: K3 (jul - sep) | E15: 31 oktober 2025
A16: K4 (okt - dec) | E16: 31 januari 2026

Sheet Inkomsten
A1: INKOMSTEN — Zeker ZZP
A2: Voer hieronder elke betaalde factuur in. Bedragen altijd EXCLUSIEF BTW.
A4: # | B4: Datum | C4: Omschrijving | D4: Klant | E4: Factuurnummer | F4: Excl. BTW (€) | G4: BTW % | H4: BTW (€) | I4: Incl. BTW (€) | J4: Categorie
A5: 1 | B5: 01-04-2025 | C5: Website bouwen | D5: Bedrijf BV | E5: 2025-001 | F5: 1500 | G5: 21 | H5: =F5*G5/100 | I5: =F5+H5 | J5: Dienstverlening
A6: 2 | B6: 15-04-2025 | C6: Consultancy april | D6: Klant NL | E6: 2025-002 | F6: 2200 | G6: 21 | H6: =F6*G6/100 | I6: =F6+H6 | J6: Advies
H7: =IF(F7="","",F7*G7/100) | I7: =IF(F7="","",F7+H7)
H8: =IF(F8="","",F8*G8/100) | I8: =IF(F8="","",F8+H8)
H9: =IF(F9="","",F9*G9/100) | I9: =IF(F9="","",F9+H9)
H10: =IF(F10="","",F10*G10/100) | I10: =IF(F10="","",F10+H10)
H11: =IF(F11="","",F11*G11/100) | I11: =IF(F11="","",F11+H11)
H12: =IF(F12="","",F12*G12/100) | I12: =IF(F12="","",F12+H12)
H13: =IF(F13="","",F13*G13/100) | I13: =IF(F13="","",F13+H13)
H14: =IF(F14="","",F14*G14/100) | I14: =IF(F14="","",F14+H14)
H15: =IF(F15="","",F15*G15/100) | I15: =IF(F15="","",F15+H15)
H16: =IF(F16="","",F16*G16/100) | I16: =IF(F16="","",F16+H16)
H17: =IF(F17="","",F17*G17/100) | I17: =IF(F17="","",F17+H17)
H18: =IF(F18="","",F18*G18/100) | I18: =IF(F18="","",F18+H18)
... H26: =IF(F26="","",F26*G26/100) | I26: =IF(F26="","",F26+H26)
A27: TOTAAL | F27: =SUM(F5:F26) | H27: =SUM(H5:H26) | I27: =SUM(I5:I26)

Sheet Uitgaven
A1: UITGAVEN — Zeker ZZP
A2: Voer hieronder je zakelijke kosten in. De BTW die je betaalt kun je terugvragen van de Belastingdienst.
A4: # | B4: Datum | C4: Omschrijving | D4: Leverancier | E4: Categorie | F4: Excl. BTW (€) | G4: BTW % | H4: BTW terug (€) | I4: Incl. BTW (€) | J4: Notitie
A5: 1 | B5: 02-04-2025 | C5: Adobe abonnement | D5: Adobe | E5: Software | F5: 49.58 | G5: 21 | H5: =F5*G5/100 | I5: =F5+H5 | J5: Maandelijks
A6: 2 | B6: 10-04-2025 | C6: Kantoorbenodigdheden | D6: Staples | E6: Kantoor | F6: 85 | G6: 21 | H6: =F6*G6/100 | I6: =F6+H6
H7: =IF(F7="","",F7*G7/100) | I7: =IF(F7="","",F7+H7)
H8: =IF(F8="","",F8*G8/100) | I8: =IF(F8="","",F8+H8)
H9: =IF(F9="","",F9*G9/100) | I9: =IF(F9="","",F9+H9)
H10: =IF(F10="","",F10*G10/100) | I10: =IF(F10="","",F10+H10)
H11: =IF(F11="","",F11*G11/100) | I11: =IF(F11="","",F11+H11)
H12: =IF(F12="","",F12*G12/100) | I12: =IF(F12="","",F12+H12)
H13: =IF(F13="","",F13*G13/100) | I13: =IF(F13="","",F13+H13)
H14: =IF(F14="","",F14*G14/100) | I14: =IF(F14="","",F14+H14)
H15: =IF(F15="","",F15*G15/100) | I15: =IF(F15="","",F15+H15)
H16: =IF(F16="","",F16*G16/100) | I16: =IF(F16="","",F16+H16)
H17: =IF(F17="","",F17*G17/100) | I17: =IF(F17="","",F17+H17)
H18: =IF(F18="","",F18*G18/100) | I18: =IF(F18="","",F18+H18)
... H26: =IF(F26="","",F26*G26/100) | I26: =IF(F26="","",F26+H26)
A27: TOTAAL | F27: =SUM(F5:F26) | H27: =SUM(H5:H26) | I27: =SUM(I5:I26)

Sheet BTW-aangifte
A1: BTW-AANGIFTE — Zeker ZZP
A3: BTW BEREKENING
A4: BTW ontvangen van klanten | B4: =SUM(Inkomsten!H5:H26) | C4: Rubriek 1a (omzet belast met 21%)
A5: BTW betaald op kosten (aftrekbaar) | B5: =SUM(Uitgaven!H5:H26) | C5: Rubriek 5b (voorbelasting)
A6: BTW-saldo (te betalen / terug) | B6: =B4-B5 | C6: Positief = betalen, Negatief = terug
A8: OMZET OVERZICHT
A9: Totale omzet excl. BTW | B9: =SUM(Inkomsten!F5:F26) | C9: Vul in bij rubriek 1a
A10: Totale kosten excl. BTW | B10: =SUM(Uitgaven!F5:F26)
A11: Winst (voor belasting) | B11: =B9-B10 | C11: Omzet minus kosten
A12: Netto in je zak (na BTW) | B12: =B11-IF(B6>0,B6,0) | C12: Winst minus BTW-betaling
A14: STAPPENPLAN BTW-AANGIFTE
A15: Stap 1 | B15: Log in op Mijn Belastingdienst Zakelijk
A16: Stap 2 | B16: Ga naar BTW-aangifte en kies het juiste kwartaal
A17: Stap 3 | B17: Vul bij rubriek 1a in: zie cel B9 (omzet)
A18: Stap 4 | B18: Vul bij rubriek 5b in: zie cel B5 (voorbelasting)
A19: Stap 5 | B19: Controleer het saldo en betaal of ontvang
